.gitignore
.gitmodules
CMakeLists.txt
LICENSE
MANIFEST.in
README.md
setup.py
LinkPython.egg-info/PKG-INFO
LinkPython.egg-info/SOURCES.txt
LinkPython.egg-info/dependency_links.txt
LinkPython.egg-info/not-zip-safe
LinkPython.egg-info/top_level.txt
example/LinkHut.py
modules/link/.appveyor.yml
modules/link/.clang-format
modules/link/.git
modules/link/.gitignore
modules/link/.gitmodules
modules/link/.travis.yml
modules/link/Ableton Link Guidelines.pdf
modules/link/AbletonLinkConfig.cmake
modules/link/CMakeLists.txt
modules/link/CONTRIBUTING.md
modules/link/GNU-GPL-v2.0.md
modules/link/LICENSE.md
modules/link/README.md
modules/link/TEST-PLAN.md
modules/link/assets/Ableton_Link_Badge-Black.eps
modules/link/assets/Ableton_Link_Badge-White.eps
modules/link/assets/Ableton_Link_Button_disabled.eps
modules/link/assets/Ableton_Link_Button_enabled.eps
modules/link/ci/build.py
modules/link/ci/check-formatting.py
modules/link/ci/configure.py
modules/link/ci/memcheck.supp
modules/link/ci/run-tests.py
modules/link/ci/run_valgrind_tests.sh
modules/link/cmake_include/AsioStandaloneConfig.cmake
modules/link/cmake_include/CatchConfig.cmake
modules/link/cmake_include/ConfigureCompileFlags.cmake
modules/link/examples/CMakeLists.txt
modules/link/examples/esp32/.gitignore
modules/link/examples/esp32/CMakeLists.txt
modules/link/examples/esp32/README.md
modules/link/examples/esp32/sdkconfig.defaults
modules/link/examples/esp32/main/CMakeLists.txt
modules/link/examples/esp32/main/main.cpp
modules/link/examples/linkaudio/AudioEngine.cpp
modules/link/examples/linkaudio/AudioEngine.hpp
modules/link/examples/linkaudio/AudioPlatform.hpp
modules/link/examples/linkaudio/AudioPlatform_Asio.cpp
modules/link/examples/linkaudio/AudioPlatform_Asio.hpp
modules/link/examples/linkaudio/AudioPlatform_CoreAudio.cpp
modules/link/examples/linkaudio/AudioPlatform_CoreAudio.hpp
modules/link/examples/linkaudio/AudioPlatform_Dummy.hpp
modules/link/examples/linkaudio/AudioPlatform_Jack.cpp
modules/link/examples/linkaudio/AudioPlatform_Jack.hpp
modules/link/examples/linkaudio/AudioPlatform_Portaudio.cpp
modules/link/examples/linkaudio/AudioPlatform_Portaudio.hpp
