Metadata-Version: 1.2
Name: LinkPython
Version: 0.1.1
Summary: Python wrapper for Ableton Link
Home-page: https://github.com/gonzaloflirt/link-python
Maintainer: Gonzalo Flirt, Damián Silvani
Maintainer-email: munshkr@gmail.com
License: UNKNOWN
Platform: UNKNOWN
